confboy1/__init__.py
confboy1-1.1.2.dist-info/LICENSE
confboy1-1.1.2.dist-info/METADATA
confboy1-1.1.2.dist-info/WHEEL
confboy1-1.1.2.dist-info/top_level.txt
confboy1-1.1.2.dist-info/RECORD
