Metadata-Version: 2.1
Name: confboy1
Version: 1.1.2
Summary: Better configs with TOML support
Author-email: Euromancer <info@realpython.com>
License: MIT License
Project-URL: Homepage, https://github.com/UlfR/confboy
Keywords: toml,config,confboy
Classifier: License :: OSI Approved :: MIT License
Classifier: Programming Language :: Python
Classifier: Programming Language :: Python :: 3
Requires-Python: >=3.7
License-File: LICENSE
Requires-Dist: toml ==0.10.2
